pyfurnace/__init__.py
pyfurnace/__main__.py
pyfurnace/app/__init__.py
pyfurnace/app/streamlit_app.py
pyfurnace/app/pages/0_Home.py
pyfurnace/app/pages/1_Design.py
pyfurnace/app/pages/2_Generate.py
pyfurnace/app/pages/3_Convert.py
pyfurnace/app/pages/4_Prepare.py
pyfurnace/app/pages/__init__.py
pyfurnace/app/static/LICENSE.TXT
pyfurnace/app/static/logo.png
pyfurnace/app/static/logo_text.png
pyfurnace/app/static/pyfurnace.svg
pyfurnace/app/utils/__init__.py
pyfurnace/app/utils/design_functions.py
pyfurnace/app/utils/motifs_icons.py
pyfurnace/app/utils/st_fixed_container.py
pyfurnace/app/utils/template_functions.py
pyfurnace/app/utils/commands/__init__.py
pyfurnace/app/utils/commands/aptamers_command.py
pyfurnace/app/utils/commands/connections_command.py
pyfurnace/app/utils/commands/dovetail_command.py
pyfurnace/app/utils/commands/general_edit_command.py
pyfurnace/app/utils/commands/kissing_loops_command.py
pyfurnace/app/utils/commands/motif_command.py
pyfurnace/app/utils/commands/stem_command.py
pyfurnace/app/utils/commands/structural_command.py
pyfurnace/app/utils/commands/tetraloop_command.py
pyfurnace/design/__init__.py
pyfurnace/design/core/__init__.py
pyfurnace/design/core/basepair.py
pyfurnace/design/core/callback.py
pyfurnace/design/core/coordinates_3d.py
pyfurnace/design/core/motif.py
pyfurnace/design/core/origami.py
pyfurnace/design/core/position.py
pyfurnace/design/core/sequence.py
pyfurnace/design/core/strand.py
pyfurnace/design/core/symbols.py
pyfurnace/design/motifs/__init__.py
pyfurnace/design/motifs/aptamers.py
pyfurnace/design/motifs/dovetail.py
pyfurnace/design/motifs/kissing_loops.py
pyfurnace/design/motifs/loops.py
pyfurnace/design/motifs/stem.py
pyfurnace/design/motifs/structural.py
pyfurnace/design/motifs/conf_files/Bend90.dat
pyfurnace/design/motifs/conf_files/Bend90_2.dat
pyfurnace/design/motifs/conf_files/Biotin.dat
pyfurnace/design/motifs/conf_files/BranchedKissingLoop.dat
pyfurnace/design/motifs/conf_files/BranchedKissingLoop_1.dat
pyfurnace-1.1.1.dist-info/licenses/LICENSE
pyfurnace-1.1.1.dist-info/METADATA
pyfurnace-1.1.1.dist-info/WHEEL
pyfurnace-1.1.1.dist-info/entry_points.txt
pyfurnace-1.1.1.dist-info/top_level.txt
pyfurnace-1.1.1.dist-info/RECORD
