Metadata-Version: 2.4
Name: pyfurnace
Version: 1.1.1
Summary: An integrated design engine for RNA origami
Author-email: Luca Monari <l.monari@zmbh.uni-heidelberg.de>
License-Expression: GPL-3.0-or-later
Keywords: RNA,DNA,nucleic acids,bioinformatics,design
Classifier: Development Status :: 3 - Alpha
Classifier: Programming Language :: Python :: 3.12
Classifier: Intended Audience :: Science/Research
Classifier: Topic :: Scientific/Engineering :: Bio-Informatics
Requires-Python: >=3.10
License-File: LICENSE
Requires-Dist: colour
Requires-Dist: pytest
Requires-Dist: numpy
Requires-Dist: scipy
Requires-Dist: matplotlib
Requires-Dist: streamlit<=1.51,>=1.48
Requires-Dist: st-click-detector
Requires-Dist: streamlit_code_editor
Requires-Dist: st_forna_component
Requires-Dist: streamlit_option_menu
Requires-Dist: st-oxview
Requires-Dist: biopython
Requires-Dist: ViennaRNA
Provides-Extra: dev
Requires-Dist: black; extra == "dev"
Requires-Dist: flake8; extra == "dev"
Requires-Dist: mypy; extra == "dev"
Requires-Dist: pytest; extra == "dev"
Requires-Dist: Flake8-pyproject; extra == "dev"
Requires-Dist: sphinxcontrib-bibtex; extra == "dev"
Requires-Dist: sphinx-autodoc-typehints; extra == "dev"
Requires-Dist: sphinx-rtd-theme; extra == "dev"
Requires-Dist: sphinx-copybutton; extra == "dev"
Requires-Dist: sphinx; extra == "dev"
Dynamic: license-file
